ngab/__init__.py
ngab/_dataset.py
ngab/_train.py
ngab/_train_utils.py
ngab/chem/__init__.py
ngab/chem/_chem.py
ngab/heterophily/__init__.py
ngab/heterophily/computation.py
ngab/heterophily/dirichlet.py
ngab/heterophily/gat.py
ngab/heterophily/gcn.py
ngab/models/__init__.py
ngab/models/_gat.py
ngab/models/_gated_gcn.py
ngab/models/_gatv2.py
ngab/models/_gcn.py
ngab/models/_gin.py
ngab/models/_graphgps.py
ngab/models/_pan.py
ngab/models/_pna.py
ngab/models/_sgc.py
ngab/models/_taggcn.py
ngab/random/__init__.py
ngab/random/_random.py
ngab-0.1.1.dist-info/METADATA
ngab-0.1.1.dist-info/WHEEL
ngab-0.1.1.dist-info/licenses/LICENSE
ngab-0.1.1.dist-info/RECORD
